MANIFEST.in
README.rst
setup.py
indev/__init__.py
indev/_log.py
indev/decorators.py
indev.egg-info/PKG-INFO
indev.egg-info/SOURCES.txt
indev.egg-info/dependency_links.txt
indev.egg-info/not-zip-safe
indev.egg-info/top_level.txt