Metadata-Version: 1.1
Name: indev
Version: 0.0.1
Summary: Package containing some basic developer helpers
Home-page: https://github.com/BhMbOb/Py-InDev
Author: Bailey3D
Author-email: contact@bailey3d.com
License: MIT
Keywords: developer indev helpers todo decorators
Platform: UNKNOWN
Classifier: Development Status :: 3 - Alpha
Classifier: License :: OSI Approved :: MIT License
Classifier: Programming Language :: Python :: 3
Classifier: Operating System :: OS Independent
